nbdev_cards/__init__.py
nbdev_cards/_modidx.py
nbdev_cards/card.py
nbdev_cards/core.py
nbdev_cards/deck.py
nbdev_cards3.14-0.0.2.dist-info/LICENSE
nbdev_cards3.14-0.0.2.dist-info/METADATA
nbdev_cards3.14-0.0.2.dist-info/WHEEL
nbdev_cards3.14-0.0.2.dist-info/entry_points.txt
nbdev_cards3.14-0.0.2.dist-info/top_level.txt
nbdev_cards3.14-0.0.2.dist-info/RECORD
